docs/conf.py
pydriftn-0.1.4.dist-info/licenses/LICENSE
src/pydriftn/DriftAstrom.py
src/pydriftn/DriftClassify.py
src/pydriftn/DriftExtract.py
src/pydriftn/DriftReposition.py
src/pydriftn/DriftSkysub.py
src/pydriftn/GenerateCatalogue.py
src/pydriftn/Utils.py
pydriftn-0.1.4.dist-info/METADATA
pydriftn-0.1.4.dist-info/WHEEL
pydriftn-0.1.4.dist-info/top_level.txt
pydriftn-0.1.4.dist-info/RECORD
