Metadata-Version: 2.4
Name: pydriftn
Version: 0.1.4
Summary: Microlensing Driftscan Project
Author-email: Kenneth Freeman <kenneth.freeman@anu.edu.au>, Renee Grace Key <rkey@swin.edu.au>, Brent Miszalski <brent.miszalski@mq.edu.au>
License: MIT License
Project-URL: Source, https://dev.aao.org.au/adacs-odc/freeman-2022b
Classifier: Development Status :: 2 - Pre-Alpha
Classifier: Intended Audience :: Science/Research
Classifier: License :: OSI Approved :: MIT License
Classifier: Programming Language :: Python :: 3
Requires-Python: >=3
License-File: LICENSE
Dynamic: license-file
